miqro_rutos_sms/__init__.py
miqro_rutos_sms/service.py
miqro_rutos_sms-0.1.1.dist-info/entry_points.txt
miqro_rutos_sms-0.1.1.dist-info/WHEEL
miqro_rutos_sms-0.1.1.dist-info/METADATA
miqro_rutos_sms-0.1.1.dist-info/RECORD
