Metadata-Version: 2.1
Name: miqro-rutos-sms
Version: 0.1.1
Summary: 
Author: Daniel Fett
Author-email: fett@danielfett.de
Requires-Python: >=3.7,<4.0
Classifier: Programming Language :: Python :: 3
Classifier: Programming Language :: Python :: 3.7
Classifier: Programming Language :: Python :: 3.8
Classifier: Programming Language :: Python :: 3.9
Classifier: Programming Language :: Python :: 3.10
Requires-Dist: miqro (>=1.2.0,<2.0.0)
Requires-Dist: requests (>=2.28.1,<3.0.0)
